<?xml version="1.0" encoding="utf-8"?>
<openerp>
    <data>
        <record id="view_order_form_alloc" model="ir.ui.view">
            <field name="name">sale.order.form.alloc</field>
            <field name="model">sale.order</field>
            <field name="inherit_id" ref="sale.view_order_form"/>
            <field name="arch" type="xml">
                <page string="Order Lines" position="after">
                    <page string="Procurements">
                        <group string="Procurements">
                            <field name="procurement_ids" nolabel="1" colspan="4"/>
                        </group>
                    </page>
                </page>
            </field>
        </record>
    </data>
</openerp>
